{
  "group": "arcfox",
  "makes": [
    {
      "name": "Arcfox",
      "models": [
        {
          "name": "Alpha S",
          "yearStart": 2024,
          "yearEnd": null,
          "generations": [
            {
              "name": "Alpha S (2024)",
              "yearStart": 2024,
              "yearEnd": null,
              "bodyType": null,
              "engines": [
                {
                  "label": "65.6 KWh RWD (218 HP)",
                  "fuelType": "Electric",
                  "cylinders": null,
                  "displacementCc": null,
                  "powerHp": 218,
                  "torqueNm": null,
                  "transmission": "1-automatic speed",
                  "drivetrain": "Rear Wheel Drive",
                  "zeroToHundredKmhS": 7.7,
                  "topSpeedKmh": null,
                  "fuelEconomyCombinedL100": null,
                  "lengthMm": 4930,
                  "widthMm": 1941,
                  "heightMm": 1600,
                  "wheelbaseMm": 2916,
                  "curbWeightKg": null,
                  "specs": {
                    "ENGINE SPECS / Electrical motor power": "160 kw (218 hp, 215 bhp)",
                    "ENGINE SPECS / Electrical motor torque": "265.5 lb-ft (360 Nm)",
                    "ENGINE SPECS / Total maximum power": "160 kw (218 hp, 215 bhp)",
                    "ENGINE SPECS / Total maximum torque": "265.5 lb-ft (360 Nm)",
                    "ENGINE SPECS / Fuel System": "Electric",
                    "ENGINE SPECS / Fuel": "Electric",
                    "PERFORMANCE SPECS / Acceleration 0-62 Mph (0-100 kph)": "7.7 s",
                    "TRANSMISSION SPECS / Drive Type": "Rear Wheel Drive",
                    "TRANSMISSION SPECS / Gearbox": "1-automatic speed",
                    "BRAKES SPECS / Front": "Ventilated disc",
                    "BRAKES SPECS / Rear": "Venilated disc",
                    "TIRES SPECS / Tire Size": "235/50 R19",
                    "DIMENSIONS / Length": "194.1 in (4930 mm)",
                    "DIMENSIONS / Width": "76.4 in (1941 mm)",
                    "DIMENSIONS / Height": "63 in (1600 mm)",
                    "DIMENSIONS / Wheelbase": "114.8 in (2916 mm)",
                    "DIMENSIONS / Ground Clearance": "5.5 in (140 mm)",
                    "DIMENSIONS / Cargo Volume": "19.8 cuFT (561 L)",
                    "DIMENSIONS / Aerodynamics (Cd)": "0.25",
                    "POWER SYSTEM SPECS / Power pack": "Intelligent constant temperature ternary lithium battery pack (IP68)",
                    "POWER SYSTEM SPECS / Maximum Capacity": "65.6 kWh"
                  }
                },
                {
                  "label": "65.6 KWh RWD (238 HP)",
                  "fuelType": "Electric",
                  "cylinders": null,
                  "displacementCc": null,
                  "powerHp": 238,
                  "torqueNm": null,
                  "transmission": "1-automatic speed",
                  "drivetrain": "Rear Wheel Drive",
                  "zeroToHundredKmhS": 8.3,
                  "topSpeedKmh": null,
                  "fuelEconomyCombinedL100": null,
                  "lengthMm": 4930,
                  "widthMm": 1941,
                  "heightMm": 1600,
                  "wheelbaseMm": 2916,
                  "curbWeightKg": null,
                  "specs": {
                    "ENGINE SPECS / Electrical motor power": "175 kw (238 hp, 235 bhp)",
                    "ENGINE SPECS / Electrical motor torque": "265.5 lb-ft (360 Nm)",
                    "ENGINE SPECS / Total maximum power": "175 kw (238 hp, 235 bhp)",
                    "ENGINE SPECS / Total maximum torque": "265.5 lb-ft (360 Nm)",
                    "ENGINE SPECS / Fuel System": "Electric",
                    "ENGINE SPECS / Fuel": "Electric",
                    "PERFORMANCE SPECS / Acceleration 0-62 Mph (0-100 kph)": "8.3 s",
                    "TRANSMISSION SPECS / Drive Type": "Rear Wheel Drive",
                    "TRANSMISSION SPECS / Gearbox": "1-automatic speed",
                    "BRAKES SPECS / Front": "Ventilated disc",
                    "BRAKES SPECS / Rear": "Venilated disc",
                    "TIRES SPECS / Tire Size": "235/50 R19",
                    "DIMENSIONS / Length": "194.1 in (4930 mm)",
                    "DIMENSIONS / Width": "76.4 in (1941 mm)",
                    "DIMENSIONS / Height": "63 in (1600 mm)",
                    "DIMENSIONS / Wheelbase": "114.8 in (2916 mm)",
                    "DIMENSIONS / Ground Clearance": "5.5 in (140 mm)",
                    "DIMENSIONS / Cargo Volume": "19.8 cuFT (561 L)",
                    "DIMENSIONS / Aerodynamics (Cd)": "0.25",
                    "POWER SYSTEM SPECS / Power pack": "Intelligent constant temperature ternary lithium battery pack (IP68)",
                    "POWER SYSTEM SPECS / Maximum Capacity": "65.6 kWh"
                  }
                },
                {
                  "label": "93.6 KWh AWD (435 HP)",
                  "fuelType": "Electric",
                  "cylinders": null,
                  "displacementCc": null,
                  "powerHp": 435,
                  "torqueNm": null,
                  "transmission": "1-automatic speed",
                  "drivetrain": "All Wheel Drive",
                  "zeroToHundredKmhS": 4.2,
                  "topSpeedKmh": null,
                  "fuelEconomyCombinedL100": null,
                  "lengthMm": 4930,
                  "widthMm": 1941,
                  "heightMm": 1600,
                  "wheelbaseMm": 2916,
                  "curbWeightKg": null,
                  "specs": {
                    "ENGINE SPECS / Electrical motor power": "320 kw (435 hp, 429 bhp)",
                    "ENGINE SPECS / Total maximum power": "320 kw (435 hp, 429 bhp)",
                    "ENGINE SPECS / Total maximum torque": "531 lb-ft (720 Nm)",
                    "ENGINE SPECS / Fuel System": "Electric",
                    "ENGINE SPECS / Fuel": "Electric",
                    "PERFORMANCE SPECS / Acceleration 0-62 Mph (0-100 kph)": "4.2 s",
                    "TRANSMISSION SPECS / Drive Type": "All Wheel Drive",
                    "TRANSMISSION SPECS / Gearbox": "1-automatic speed",
                    "BRAKES SPECS / Front": "Ventilated disc",
                    "BRAKES SPECS / Rear": "Venilated disc",
                    "TIRES SPECS / Tire Size": "245/45 R20",
                    "DIMENSIONS / Length": "194.1 in (4930 mm)",
                    "DIMENSIONS / Width": "76.4 in (1941 mm)",
                    "DIMENSIONS / Height": "63 in (1600 mm)",
                    "DIMENSIONS / Wheelbase": "114.8 in (2916 mm)",
                    "DIMENSIONS / Ground Clearance": "5.5 in (140 mm)",
                    "DIMENSIONS / Cargo Volume": "19.8 cuFT (561 L)",
                    "DIMENSIONS / Aerodynamics (Cd)": "0.25",
                    "POWER SYSTEM SPECS / Power pack": "Intelligent constant temperature ternary lithium battery pack (IP68)",
                    "POWER SYSTEM SPECS / Maximum Capacity": "93.6 kWh"
                  }
                },
                {
                  "label": "94.5 KWh AWD (435 HP)",
                  "fuelType": "Electric",
                  "cylinders": null,
                  "displacementCc": null,
                  "powerHp": 435,
                  "torqueNm": null,
                  "transmission": "1-automatic speed",
                  "drivetrain": "All Wheel Drive",
                  "zeroToHundredKmhS": 8.3,
                  "topSpeedKmh": null,
                  "fuelEconomyCombinedL100": null,
                  "lengthMm": 4930,
                  "widthMm": 1941,
                  "heightMm": 1600,
                  "wheelbaseMm": 2916,
                  "curbWeightKg": null,
                  "specs": {
                    "ENGINE SPECS / Electrical motor power": "320 kw (435 hp, 429 bhp)",
                    "ENGINE SPECS / Total maximum power": "320 kw (435 hp, 429 bhp)",
                    "ENGINE SPECS / Total maximum torque": "531 lb-ft (720 Nm)",
                    "ENGINE SPECS / Fuel System": "Electric",
                    "ENGINE SPECS / Fuel": "Electric",
                    "PERFORMANCE SPECS / Acceleration 0-62 Mph (0-100 kph)": "8.3 s",
                    "TRANSMISSION SPECS / Drive Type": "All Wheel Drive",
                    "TRANSMISSION SPECS / Gearbox": "1-automatic speed",
                    "BRAKES SPECS / Front": "Ventilated disc",
                    "BRAKES SPECS / Rear": "Venilated disc",
                    "TIRES SPECS / Tire Size": "235/50 R19",
                    "DIMENSIONS / Length": "194.1 in (4930 mm)",
                    "DIMENSIONS / Width": "76.4 in (1941 mm)",
                    "DIMENSIONS / Height": "63 in (1600 mm)",
                    "DIMENSIONS / Wheelbase": "114.8 in (2916 mm)",
                    "DIMENSIONS / Ground Clearance": "5.5 in (140 mm)",
                    "DIMENSIONS / Cargo Volume": "19.8 cuFT (561 L)",
                    "DIMENSIONS / Aerodynamics (Cd)": "0.25",
                    "POWER SYSTEM SPECS / Power pack": "Intelligent constant temperature ternary lithium battery pack (IP68)",
                    "POWER SYSTEM SPECS / Maximum Capacity": "94.5 kWh"
                  }
                }
              ]
            }
          ]
        },
        {
          "name": "Alpha T",
          "yearStart": 2024,
          "yearEnd": null,
          "generations": [
            {
              "name": "Alpha T (2024)",
              "yearStart": 2024,
              "yearEnd": null,
              "bodyType": null,
              "engines": [
                {
                  "label": "65.6 KWh RWD (238 HP)",
                  "fuelType": "Electric",
                  "cylinders": null,
                  "displacementCc": null,
                  "powerHp": 238,
                  "torqueNm": null,
                  "transmission": "1-automatic speed",
                  "drivetrain": "Rear Wheel Drive",
                  "zeroToHundredKmhS": 8,
                  "topSpeedKmh": null,
                  "fuelEconomyCombinedL100": null,
                  "lengthMm": 4788,
                  "widthMm": 1941,
                  "heightMm": 1684,
                  "wheelbaseMm": 2916,
                  "curbWeightKg": null,
                  "specs": {
                    "ENGINE SPECS / Electrical motor power": "175 kw (238 hp, 235 bhp)",
                    "ENGINE SPECS / Total maximum power": "175 kw (238 hp, 235 bhp)",
                    "ENGINE SPECS / Total maximum torque": "265.5 lb-ft (360 Nm)",
                    "ENGINE SPECS / Fuel System": "Electric",
                    "ENGINE SPECS / Fuel": "Electric",
                    "PERFORMANCE SPECS / Acceleration 0-62 Mph (0-100 kph)": "8 s",
                    "TRANSMISSION SPECS / Drive Type": "Rear Wheel Drive",
                    "TRANSMISSION SPECS / Gearbox": "1-automatic speed",
                    "BRAKES SPECS / Front": "Ventilated disc",
                    "BRAKES SPECS / Rear": "Disc",
                    "TIRES SPECS / Tire Size": "235/50 R19",
                    "DIMENSIONS / Length": "188.5 in (4788 mm)",
                    "DIMENSIONS / Width": "76.4 in (1941 mm)",
                    "DIMENSIONS / Height": "66.3 in (1684 mm)",
                    "DIMENSIONS / Wheelbase": "114.8 in (2916 mm)",
                    "DIMENSIONS / Ground Clearance": "6.3 in (160 mm)",
                    "DIMENSIONS / Cargo Volume": "16.3 cuFT (462 L)",
                    "DIMENSIONS / Aerodynamics (Cd)": "0.271",
                    "POWER SYSTEM SPECS / Power pack": "Lithium-ion (Li-Ion)",
                    "POWER SYSTEM SPECS / Maximum Capacity": "65.6 kWh"
                  }
                },
                {
                  "label": "93.6 KWh AWD (435 HP)",
                  "fuelType": "Electric",
                  "cylinders": null,
                  "displacementCc": null,
                  "powerHp": 435,
                  "torqueNm": null,
                  "transmission": "1-automatic speed",
                  "drivetrain": "All Wheel Drive",
                  "zeroToHundredKmhS": 4.6,
                  "topSpeedKmh": null,
                  "fuelEconomyCombinedL100": null,
                  "lengthMm": 4788,
                  "widthMm": 1941,
                  "heightMm": 1684,
                  "wheelbaseMm": 2916,
                  "curbWeightKg": null,
                  "specs": {
                    "ENGINE SPECS / Electrical motor power": "320 kw (435 hp, 429 bhp)",
                    "ENGINE SPECS / Total maximum power": "320 kw (435 hp, 429 bhp)",
                    "ENGINE SPECS / Total maximum torque": "531 lb-ft (720 Nm)",
                    "ENGINE SPECS / Fuel System": "Electric",
                    "ENGINE SPECS / Fuel": "Electric",
                    "PERFORMANCE SPECS / Acceleration 0-62 Mph (0-100 kph)": "4.6 s",
                    "TRANSMISSION SPECS / Drive Type": "All Wheel Drive",
                    "TRANSMISSION SPECS / Gearbox": "1-automatic speed",
                    "BRAKES SPECS / Front": "Ventilated disc",
                    "BRAKES SPECS / Rear": "Disc",
                    "TIRES SPECS / Tire Size": "245/45 R20",
                    "DIMENSIONS / Length": "188.5 in (4788 mm)",
                    "DIMENSIONS / Width": "76.4 in (1941 mm)",
                    "DIMENSIONS / Height": "66.3 in (1684 mm)",
                    "DIMENSIONS / Wheelbase": "114.8 in (2916 mm)",
                    "DIMENSIONS / Ground Clearance": "6.3 in (160 mm)",
                    "DIMENSIONS / Cargo Volume": "16.3 cuFT (462 L)",
                    "DIMENSIONS / Aerodynamics (Cd)": "0.271",
                    "POWER SYSTEM SPECS / Power pack": "Lithium-ion (Li-Ion)",
                    "POWER SYSTEM SPECS / Maximum Capacity": "93.6 kWh",
                    "POWER SYSTEM SPECS / Range": "339.3 miles (546.0 km)"
                  }
                }
              ]
            }
          ]
        }
      ]
    }
  ]
}
